FDEasyChainSDK/__init__.py
FDEasyChainSDK/core.py
FDEasyChainSDK/exceptions.py
FDEasyChainSDK/utils/__init__.py
official/demo.py
FDEasyChainSDK-1.5.0.dist-info/LICENSE
FDEasyChainSDK-1.5.0.dist-info/METADATA
FDEasyChainSDK-1.5.0.dist-info/WHEEL
FDEasyChainSDK-1.5.0.dist-info/top_level.txt
FDEasyChainSDK-1.5.0.dist-info/RECORD
