Metadata-Version: 2.2
Name: FDEasyChainSDK
Version: 1.5.0
Summary: 五度易链SDK - 企业数据查询接口
Author-email: Sadam·Sadik <1903249375@qq.com>
License: MIT License
Classifier: Programming Language :: Python :: 3
Classifier: License :: OSI Approved :: MIT License
Classifier: Operating System :: OS Independent
Requires-Python: >=3.6
License-File: LICENSE
Requires-Dist: requests>=2.25.0
Requires-Dist: python-dotenv>=0.19.0
Requires-Dist: colorlog>=6.7.0
